hawkeyeZero/__init__.py
hawkeyeZero/model.py
hawkeyeZero/constants/__init__.py
hawkeyeZero/constants/model_agument_parameters.py
hawkeyeZero/constants/model_setup_parameters.py
hawkeyeZero/constants/models_to_use.py
hawkeyeZero/tests/__init__.py
hawkeyeZero/tests/test_draw_ui_detection_results.py
hawkeyeZero/tests/test_export.py
hawkeyeZero/tests/test_hawkeyezero_init.py
hawkeyeZero/tests/test_is_model_avaliable.py
hawkeyeZero/tests/test_load_path.py
hawkeyeZero/tests/test_load_yolo.py
hawkeyeZero/tests/test_train.py
hawkeyeZero/tests/test_use_model.py
hawkeyeZero/tests/test_val.py
hawkeyezero-1.0.0.dist-info/licenses/LICENSE
hawkeyezero-1.0.0.dist-info/METADATA
hawkeyezero-1.0.0.dist-info/WHEEL
hawkeyezero-1.0.0.dist-info/top_level.txt
hawkeyezero-1.0.0.dist-info/RECORD
