Metadata-Version: 2.4
Name: hawkeyezero
Version: 1.0.0
Summary: Hawkeye-Zero - special trained model to detect 11 diffrent types of space debris. The idea wasn’t to build a perfect system — just to explore how far object detection can go in real-world space debris applications. Also very important thing was to care about easy and quick access to use model functions and data, so I've created special structure for this project to allowed developers to use model in diffrent environments in API's or as a simple python tool.
Author: Gabriel Wiśniewski
Author-email: gabrys.wisniewski@op.pl
Project-URL: Source Code & Docs, https://github.com/Gabrli/Hawkeye-Zero
Keywords: yolo,computer vision,deep learning,machine learning,object detection,python,automation,data science,ai,neural networks,image processing,data preparation
Classifier: Development Status :: 4 - Beta
Classifier: Intended Audience :: Developers
Classifier: Intended Audience :: Science/Research
Classifier: Topic :: Software Development :: Libraries
Classifier: Topic :: Scientific/Engineering :: Artificial Intelligence
Classifier: Programming Language :: Python :: 3
Classifier: License :: OSI Approved :: GNU General Public License v3 (GPLv3)
Classifier: Operating System :: OS Independent
License-File: LICENSE
Requires-Dist: pyyaml
Dynamic: author
Dynamic: author-email
Dynamic: classifier
Dynamic: description
Dynamic: description-content-type
Dynamic: keywords
Dynamic: license-file
Dynamic: project-url
Dynamic: requires-dist
Dynamic: summary
